{
  "versions": [
    {
      "version": "1.0.2",
      "commit": "b4f84cb55331730ea0fc302bdaf515a84788afd9",
      "discovered": "2026-04-21T00:00:00Z"
    },
    {
      "version": "1.0.1",
      "commit": "e29990f1faef512e5a4ca91cc2e3b36597fe3426",
      "discovered": "2026-04-21T00:00:00Z"
    },
    {
      "version": "v1.0",
      "commit": "edad6583968f967a64d3d93e7355d4eb54f8cada",
      "discovered": "2026-04-21T00:00:00Z"
    },
    {
      "version": "1.0.0",
      "commit": "edad6583968f967a64d3d93e7355d4eb54f8cada",
      "discovered": "2026-04-21T00:00:00Z"
    }
  ]
}