{
  "versions": [
    {
      "version": "0.0.5",
      "commit": "cf43b7b620f2e5c268eafee5a90f1d56902e5f78",
      "discovered": "2026-04-21T00:00:00Z"
    },
    {
      "version": "0.0.4",
      "commit": "fe9ff2d884e890e2fa4b18deab7503e59077b40c",
      "discovered": "2026-04-21T00:00:00Z"
    },
    {
      "version": "0.0.3",
      "commit": "50bc70c49a9db78737e4e01aadbf7fc8d322e04b",
      "discovered": "2026-04-21T00:00:00Z"
    },
    {
      "version": "0.0.2",
      "commit": "64d748643b8da433b3c37aeaa01bbec4e4b6033c",
      "discovered": "2026-04-21T00:00:00Z"
    },
    {
      "version": "0.0.1",
      "commit": "bbfe25349ff60124dce28f950210b64dd24e89ef",
      "discovered": "2026-04-21T00:00:00Z"
    }
  ]
}