{
  "versions": [
    {
      "version": "v0.3.0",
      "commit": "5c1ba002ca5235d157264edcc546dd82ebcfe702",
      "discovered": "2026-04-21T00:00:00Z"
    },
    {
      "version": "v0.2.1",
      "commit": "4db1d375673a37965310abadad28706d8ed955f1",
      "discovered": "2026-04-21T00:00:00Z"
    },
    {
      "version": "v0.2.0",
      "commit": "b3b338eccde5ad26d3d980f050ae1b3550c863b4",
      "discovered": "2026-04-21T00:00:00Z"
    },
    {
      "version": "v0.1.0",
      "commit": "993453f6aa70d1f4370ec142107e3603d585e318",
      "discovered": "2026-04-21T00:00:00Z"
    },
    {
      "version": "v0.0.2",
      "commit": "6b2520e71922a02ac7c6752d566920b782a6d698",
      "discovered": "2026-04-21T00:00:00Z"
    },
    {
      "version": "v0.0.1",
      "commit": "e466e3b8d5d5a8898956a848a90a996bb6d85acf",
      "discovered": "2026-04-21T00:00:00Z"
    }
  ]
}