{
  "versions": [
    {
      "version": "v0.0.4",
      "commit": "80ba05470775eb33fdf4c44922c54241f944081c",
      "discovered": "2026-04-21T00:00:00Z"
    },
    {
      "version": "v0.0.3",
      "commit": "a2eee652fab205e19aa4989458ecc9eb15bbaffc",
      "discovered": "2026-04-21T00:00:00Z"
    },
    {
      "version": "v0.0.2",
      "commit": "f0dbb3f5ad879c3175e27d2252a611252c269591",
      "discovered": "2026-04-21T00:00:00Z"
    },
    {
      "version": "v0.0.1",
      "commit": "41bebb2c5191f403ea4c72fa9137266346b787d9",
      "discovered": "2026-04-21T00:00:00Z"
    }
  ]
}