{
  "versions": [
    {
      "version": "v1.0.8",
      "commit": "004bae9c94965ba40a74f36224933c5aee56b36d",
      "discovered": "2026-04-21T00:00:00Z"
    },
    {
      "version": "v1.0.7",
      "commit": "4a453c08ddd777adef631758b262fc12b983138d",
      "discovered": "2026-04-21T00:00:00Z"
    },
    {
      "version": "v1.0.6",
      "commit": "b82d965d36bc6ce9446a66bb2d3c5a24e413ad95",
      "discovered": "2026-04-21T00:00:00Z"
    },
    {
      "version": "v1.0.5",
      "commit": "414be3599e337106acd7ad8c78931a2cbff3f9e7",
      "discovered": "2026-04-21T00:00:00Z"
    },
    {
      "version": "v1.0.4",
      "commit": "ed10b3685280a4866bbd33f450f836125667fa58",
      "discovered": "2026-04-21T00:00:00Z"
    },
    {
      "version": "v1.0.3",
      "commit": "563c0d841ffbc37984007fcf73807fa8a15828cf",
      "discovered": "2026-04-21T00:00:00Z"
    },
    {
      "version": "v1.0.2",
      "commit": "4244e61a8e8b31525b7241e6a22ba7c97bd207bf",
      "discovered": "2026-04-21T00:00:00Z"
    },
    {
      "version": "v1.0.1",
      "commit": "9da17b1ba4d0d0004562cd4330cfdd0d8ff1095c",
      "discovered": "2026-04-21T00:00:00Z"
    },
    {
      "version": "v1.0.0",
      "commit": "0bfc6f0e71a3e6b058ec1df31256dae2b4d892bc",
      "discovered": "2026-04-21T00:00:00Z"
    }
  ]
}