{
  "versions": [
    {
      "version": "v3.0.1",
      "commit": "5301cdea9838330060faa846b52a7c240459d230",
      "discovered": "2026-04-21T00:00:00Z"
    },
    {
      "version": "v3.0.0",
      "commit": "81fbd8cfc6cf20e966d1d87ed4605fb434e72a7f",
      "discovered": "2026-04-21T00:00:00Z"
    },
    {
      "version": "v2.1.0",
      "commit": "f1fc31f16035cbc5a89f04f0cdba091c69e21720",
      "discovered": "2026-04-21T00:00:00Z"
    },
    {
      "version": "v2.0.0",
      "commit": "fd04dbeb62cb1838b3c3a1cc5b065c145d18ed2b",
      "discovered": "2026-04-21T00:00:00Z"
    },
    {
      "version": "v1.1.0",
      "commit": "d2b5f97c044796af23e5ff42ade717fb7a6755d1",
      "discovered": "2026-04-21T00:00:00Z"
    },
    {
      "version": "v1.0.0",
      "commit": "f47baecb3c2c51debd4bfce777332e1857cf615a",
      "discovered": "2026-04-21T00:00:00Z"
    }
  ]
}