{
  "versions": [
    {
      "version": "v3.16.0",
      "commit": "fe6d75e9571788267a8b306c4ddb5ba8355cccc0",
      "discovered": "2026-04-21T00:00:00Z"
    },
    {
      "version": "v3.15.0",
      "commit": "ca11bd5b74ce549528aa682bed92a47a4da268ab",
      "discovered": "2026-04-21T00:00:00Z"
    },
    {
      "version": "v3.14.0",
      "commit": "8e5d1320b544a459c4a49c4d610dd484ec59cc26",
      "discovered": "2026-04-21T00:00:00Z"
    },
    {
      "version": "v3.13.0",
      "commit": "88060ac85a0a92e757ecab3591a8bad69a1fa5cc",
      "discovered": "2026-04-21T00:00:00Z"
    },
    {
      "version": "v3.12.0",
      "commit": "beba11b94ed1a9cd6ba6ececdbbbcc044e0ae6c8",
      "discovered": "2026-04-21T00:00:00Z"
    },
    {
      "version": "v3.11.0",
      "commit": "06c78e68a3aa35a919f0965e0207127a8c345df3",
      "discovered": "2026-04-21T00:00:00Z"
    },
    {
      "version": "v3.10.0",
      "commit": "9324c507e68956f8726ff74b29476388c79f60f3",
      "discovered": "2026-04-21T00:00:00Z"
    },
    {
      "version": "v3.9.0",
      "commit": "e0bb342f2f4c771fffa48d333c172815475d2faa",
      "discovered": "2026-04-21T00:00:00Z"
    },
    {
      "version": "v3.8.0",
      "commit": "f5dfb4acf82ed11bbb44c9b88faa42cdd6dc6224",
      "discovered": "2026-04-21T00:00:00Z"
    },
    {
      "version": "v3.7.0",
      "commit": "f7a7af35a7ddfb8a431fb3eadfd7980cfb8c3f48",
      "discovered": "2026-04-21T00:00:00Z"
    },
    {
      "version": "v3.6.0",
      "commit": "944b487eecf385dc7683d2975ebe619b1ac0e6f6",
      "discovered": "2026-04-21T00:00:00Z"
    },
    {
      "version": "v3.5.0",
      "commit": "60490646c78fc966aa0f89d05f6ef55f499f5fa4",
      "discovered": "2026-04-21T00:00:00Z"
    },
    {
      "version": "v3.4.0",
      "commit": "ba379cac73e285eb5e3fd1ad5e5449230ee9448d",
      "discovered": "2026-04-21T00:00:00Z"
    },
    {
      "version": "v3.3.0",
      "commit": "56660d84ccf87b89f02810953df1188643ce89fa",
      "discovered": "2026-04-21T00:00:00Z"
    },
    {
      "version": "v3.2.0",
      "commit": "641cc7b8e1f8df192b098bcede9161afee611729",
      "discovered": "2026-04-21T00:00:00Z"
    },
    {
      "version": "v3.1.0",
      "commit": "39517a1859b47115865fb3006befc97f779ef475",
      "discovered": "2026-04-21T00:00:00Z"
    },
    {
      "version": "v3.0.0",
      "commit": "77d471f30799c045413ed1bee904dc13d0f30f63",
      "discovered": "2026-04-21T00:00:00Z"
    },
    {
      "version": "v2.25.0",
      "commit": "870f5fb47824d06d7934e52710ee1081fd6fb8b6",
      "discovered": "2026-04-21T00:00:00Z"
    },
    {
      "version": "v2.24.0",
      "commit": "f0990a68d48ed0ed41360d8d2053d7a4f942e7d8",
      "discovered": "2026-04-21T00:00:00Z"
    },
    {
      "version": "v2.23.0",
      "commit": "9614e78d03dc47cec84fc7e402811887b4395398",
      "discovered": "2026-04-21T00:00:00Z"
    },
    {
      "version": "v2.22.0",
      "commit": "91bc350105838ff620e4d4a355bf3d5eded20446",
      "discovered": "2026-04-21T00:00:00Z"
    },
    {
      "version": "v2.21.0",
      "commit": "1f41e62fa733c17c313b2494f02a6eec4f6ff2ea",
      "discovered": "2026-04-21T00:00:00Z"
    },
    {
      "version": "v2.20.0",
      "commit": "0a3d0388d498f7741a0689045f01c046171de9d5",
      "discovered": "2026-04-21T00:00:00Z"
    },
    {
      "version": "v2.19.0",
      "commit": "8e0d45cb56cb9a95fac44c28a2e1a2a8ce82cb0d",
      "discovered": "2026-04-21T00:00:00Z"
    },
    {
      "version": "v2.18.0",
      "commit": "d07f83e790d7d7f81035b3bf6719d33aed1d0ca0",
      "discovered": "2026-04-21T00:00:00Z"
    },
    {
      "version": "v2.17.0",
      "commit": "52e247c894ce73e2d39f69831c978f36d40b49e3",
      "discovered": "2026-04-21T00:00:00Z"
    },
    {
      "version": "v2.16.0",
      "commit": "7310455ac59449321244fb89534776b0df322948",
      "discovered": "2026-04-21T00:00:00Z"
    },
    {
      "version": "v2.15.0",
      "commit": "5ab85b0dd8e57cdd516c447f0d2f98ccfd238934",
      "discovered": "2026-04-21T00:00:00Z"
    },
    {
      "version": "v2.14.0",
      "commit": "fd4d6141bcfc84307a84a73f78321d5e2baec7f8",
      "discovered": "2026-04-21T00:00:00Z"
    },
    {
      "version": "v2.13.0",
      "commit": "a39b2eb724eeda35d0a468c8243bec87722841b2",
      "discovered": "2026-04-21T00:00:00Z"
    },
    {
      "version": "v2.12.0",
      "commit": "c09dd88079d2f4d2889922e1abf0846df2eb5611",
      "discovered": "2026-04-21T00:00:00Z"
    },
    {
      "version": "v2.11.0",
      "commit": "d7eb71cb61c31d1c0c0a6eb29fad23d05e5786f8",
      "discovered": "2026-04-21T00:00:00Z"
    },
    {
      "version": "v2.10.0",
      "commit": "b257dff2dbcda3cb82e48230db3492b98e17f859",
      "discovered": "2026-04-21T00:00:00Z"
    },
    {
      "version": "v2.9.0",
      "commit": "5d1be9459bd84de58e0bde8740f85f91f42c813d",
      "discovered": "2026-04-21T00:00:00Z"
    },
    {
      "version": "v2.8.0",
      "commit": "3934c492fadfb8d170b32736bd499f865ab2e75b",
      "discovered": "2026-04-21T00:00:00Z"
    },
    {
      "version": "v2.7.0",
      "commit": "079b4c5e8c732f4527cd7fbb513e7b575da31e0b",
      "discovered": "2026-04-21T00:00:00Z"
    },
    {
      "version": "v2.6.0",
      "commit": "de1222981594d5bc4afd775f8fc2b8ef4161ebe1",
      "discovered": "2026-04-21T00:00:00Z"
    },
    {
      "version": "v2.5.0",
      "commit": "87d8afbe5acb6177df9e79be4421840710c3c6dd",
      "discovered": "2026-04-21T00:00:00Z"
    },
    {
      "version": "v2.4.0",
      "commit": "404b7861c046c30fb0b01b261b543c727e1a25a7",
      "discovered": "2026-04-21T00:00:00Z"
    },
    {
      "version": "v2.3.0",
      "commit": "64f6192befb88936c2965117cb7fde29f78c41ab",
      "discovered": "2026-04-21T00:00:00Z"
    },
    {
      "version": "v2.2.0",
      "commit": "095591c6e719d08ca3fcbdf5796923f3f90d5a41",
      "discovered": "2026-04-21T00:00:00Z"
    },
    {
      "version": "v2.1.0",
      "commit": "42946548aee38e252589d030d160d6c1ad27dc2c",
      "discovered": "2026-04-21T00:00:00Z"
    },
    {
      "version": "v2.0.0",
      "commit": "c736c90704a72fdd2b69c31c920a54c6d0167f1d",
      "discovered": "2026-04-21T00:00:00Z"
    },
    {
      "version": "v1.0.0",
      "commit": "40788a97f968a58dc0d7cfcc0702359a0263ebf3",
      "discovered": "2026-04-21T00:00:00Z"
    },
    {
      "version": "v0.5.0",
      "commit": "b7824a53f15eef6b3db70b8736a96ad3e5e4bda9",
      "discovered": "2026-04-21T00:00:00Z"
    },
    {
      "version": "v0.4.0",
      "commit": "60c47dc10949c3275b7eae6cb4d3a05f776cd7b2",
      "discovered": "2026-04-21T00:00:00Z"
    },
    {
      "version": "v0.3.0",
      "commit": "5d0cde2f402880afda59cdda8dd587f886f3745c",
      "discovered": "2026-04-21T00:00:00Z"
    },
    {
      "version": "v0.2.0",
      "commit": "b315feb6eae1a57f090504ccb18fd89c0bad6f0e",
      "discovered": "2026-04-21T00:00:00Z"
    },
    {
      "version": "v0.1.0",
      "commit": "4d225dee8878c975689adad9188233e9f1a373c9",
      "discovered": "2026-04-21T00:00:00Z"
    },
    {
      "version": "v0.0.7",
      "commit": "8b04e3e3afd17e24bc9f7995db2692ad1229114c",
      "discovered": "2026-04-21T00:00:00Z"
    },
    {
      "version": "v0.0.6",
      "commit": "5e45e47cd2c1d6c997b771f1c976b082b0ef4acb",
      "discovered": "2026-04-21T00:00:00Z"
    },
    {
      "version": "v0.0.5",
      "commit": "eaf730b8f9b247f29ace0380e01d210d94776824",
      "discovered": "2026-04-21T00:00:00Z"
    },
    {
      "version": "v0.0.4",
      "commit": "76f6ee5dd25e925bbc935044daef3581e2fad3d5",
      "discovered": "2026-04-21T00:00:00Z"
    },
    {
      "version": "v0.0.3",
      "commit": "7504a11b1552ee85502f8d7df08d131f0a391f37",
      "discovered": "2026-04-21T00:00:00Z"
    },
    {
      "version": "v0.0.2",
      "commit": "0fd943f429ae9a94aa1c81388796b31bcec30153",
      "discovered": "2026-04-21T00:00:00Z"
    },
    {
      "version": "v0.0.1",
      "commit": "22f30d981f96a2ce0ff6e630e23629e12149ad3d",
      "discovered": "2026-04-21T00:00:00Z"
    }
  ]
}