{
  "versions": [
    {
      "version": "0.7.0",
      "commit": "86f489cda3774b40ab1ddc0c2ff6e658663130ac",
      "discovered": "2026-04-21T00:00:00Z"
    },
    {
      "version": "0.6.0",
      "commit": "ef55fbd715f6169446fa036d1d5ff1a6274cf20a",
      "discovered": "2026-04-21T00:00:00Z"
    },
    {
      "version": "0.5.0",
      "commit": "f7372a78ab8150a217f3a83f2ef15799f77e87f1",
      "discovered": "2026-04-21T00:00:00Z"
    },
    {
      "version": "0.4.0",
      "commit": "be802cad4f2ea7963df88393d52b0bcecdb55fac",
      "discovered": "2026-04-21T00:00:00Z"
    },
    {
      "version": "0.3.0",
      "commit": "7a34426d488e6f66b1cc59015687d7730d88a2d7",
      "discovered": "2026-04-21T00:00:00Z"
    },
    {
      "version": "0.2.0",
      "commit": "ea6734066242e86a398fb95dbce3908603ab8fae",
      "discovered": "2026-04-21T00:00:00Z"
    },
    {
      "version": "0.1.0",
      "commit": "0a6f55907a65b13c202d95de5bb9a6a5e5c2d194",
      "discovered": "2026-04-21T00:00:00Z"
    }
  ]
}