{
  "versions": [
    {
      "version": "v0.3.5",
      "commit": "63ddc555f56a8785b7d6d7cca2f4a4b1bb003d21",
      "discovered": "2026-04-21T00:00:00Z"
    },
    {
      "version": "v0.3.4",
      "commit": "2c2687308a0d0b7fe8601315a984481fbed56528",
      "discovered": "2026-04-21T00:00:00Z"
    },
    {
      "version": "v0.3.2",
      "commit": "1d49e972194d92d09b5c81a22c9bd7346672b30e",
      "discovered": "2026-04-21T00:00:00Z"
    },
    {
      "version": "v0.3.1",
      "commit": "68acd3caa7888dc074ccf206de46b54dbeb4e239",
      "discovered": "2026-04-21T00:00:00Z"
    },
    {
      "version": "v0.3.0",
      "commit": "e446f31b621d7ab3adcbe5db0dd6806c7efd91ad",
      "discovered": "2026-04-21T00:00:00Z"
    },
    {
      "version": "v0.2.3",
      "commit": "ff06bcd92b6812e35e966fdbde6d908e50941e98",
      "discovered": "2026-04-21T00:00:00Z"
    },
    {
      "version": "v0.2.2",
      "commit": "58827cda6dc4828a56267f270a533a86c10613b4",
      "discovered": "2026-04-21T00:00:00Z"
    },
    {
      "version": "v0.2.1",
      "commit": "757e9150a6370a39ce51c90d2b0438d318102a0c",
      "discovered": "2026-04-21T00:00:00Z"
    },
    {
      "version": "v0.2.0",
      "commit": "f2a90b0cecc06b1cf49539e7cbd0db22e824a942",
      "discovered": "2026-04-21T00:00:00Z"
    },
    {
      "version": "v0.1.2",
      "commit": "1af52c1bd6005015f803ad612c0d419e053962b9",
      "discovered": "2026-04-21T00:00:00Z"
    },
    {
      "version": "v0.1.1",
      "commit": "de9153e46a34f32b9c66f643c19f94cfb0965aa2",
      "discovered": "2026-04-21T00:00:00Z"
    },
    {
      "version": "v0.1.0",
      "commit": "11b9ad46b42182c410b76d7e033ec16e37fe9b12",
      "discovered": "2026-04-21T00:00:00Z"
    },
    {
      "version": "v0.0.9",
      "commit": "c7d55408469be180da9aa1a624ea7861cb51697c",
      "discovered": "2026-04-21T00:00:00Z"
    },
    {
      "version": "v0.0.8",
      "commit": "3fc9d052c570a956fb9c49fda08d03f493bc7a98",
      "discovered": "2026-04-21T00:00:00Z"
    },
    {
      "version": "v0.0.7",
      "commit": "179cf0b7d0f2efb897a8d99e12691ada9ad84e01",
      "discovered": "2026-04-21T00:00:00Z"
    },
    {
      "version": "v0.0.6",
      "commit": "6dff0cfc109bf839b07ff97b0e929e4691e7aa1c",
      "discovered": "2026-04-21T00:00:00Z"
    },
    {
      "version": "v0.0.5",
      "commit": "8bf03b21f2ca13cb6f245780f1114961ba6b88b8",
      "discovered": "2026-04-21T00:00:00Z"
    },
    {
      "version": "v0.0.4",
      "commit": "f5912b64cbccbcf03f2ec90fd4f4831ef35c405a",
      "discovered": "2026-04-21T00:00:00Z"
    },
    {
      "version": "v0.0.3",
      "commit": "00c733278a9f986e559f0b1f1ff234664999d6fd",
      "discovered": "2026-04-21T00:00:00Z"
    },
    {
      "version": "v0.0.2",
      "commit": "3112c3a13cb0fc348a97d297df2504572005cf27",
      "discovered": "2026-04-21T00:00:00Z"
    },
    {
      "version": "v0.0.1",
      "commit": "2af04d419346bdb8408bcf4fea39c32dc4017f34",
      "discovered": "2026-04-21T00:00:00Z"
    }
  ]
}