{
  "versions": [
    {
      "version": "v1.4.1",
      "commit": "7b61c382f9a3cd6fba3258441f02088fd36cef35",
      "discovered": "2026-04-21T00:00:00Z"
    },
    {
      "version": "v1.4.0",
      "commit": "7b61c382f9a3cd6fba3258441f02088fd36cef35",
      "discovered": "2026-04-21T00:00:00Z"
    },
    {
      "version": "v1.3.0",
      "commit": "b7180dd22241566b1eb86b8d60c187e2e6ba136a",
      "discovered": "2026-04-21T00:00:00Z"
    },
    {
      "version": "v1.2.0",
      "commit": "bd42b1f3f14f05ac092acf1540a511a584dfc7a7",
      "discovered": "2026-04-21T00:00:00Z"
    },
    {
      "version": "v1.1.15",
      "commit": "d7a735cbd399145926a8613bd4a1a8a30ec5a36b",
      "discovered": "2026-04-21T00:00:00Z"
    },
    {
      "version": "v1.1.14",
      "commit": "772ece5f9b3a153e1e4cec83b86679182439598a",
      "discovered": "2026-04-21T00:00:00Z"
    },
    {
      "version": "v1.1.13",
      "commit": "6660ebd59a23f24642c50661cb1d808eff7ce189",
      "discovered": "2026-04-21T00:00:00Z"
    },
    {
      "version": "v1.1.12",
      "commit": "8fa1f31dc780a1306a48f0081f5ca1830e1d33c4",
      "discovered": "2026-04-21T00:00:00Z"
    },
    {
      "version": "v1.1.11",
      "commit": "c6657a6059154c577dbd438e4b82e28f32f05aaf",
      "discovered": "2026-04-21T00:00:00Z"
    },
    {
      "version": "v1.1.10",
      "commit": "d7bfde3b1a94411cad141d6e07e513fab5dfb092",
      "discovered": "2026-04-21T00:00:00Z"
    },
    {
      "version": "v1.1.9",
      "commit": "bc9835c1b81a3e3d95a3cd51e59828024773503b",
      "discovered": "2026-04-21T00:00:00Z"
    },
    {
      "version": "v1.1.8",
      "commit": "bc9835c1b81a3e3d95a3cd51e59828024773503b",
      "discovered": "2026-04-21T00:00:00Z"
    },
    {
      "version": "1.1.8",
      "commit": "bc9835c1b81a3e3d95a3cd51e59828024773503b",
      "discovered": "2026-04-21T00:00:00Z"
    },
    {
      "version": "v1.1.7",
      "commit": "39fe50664a47564893ecdfdb4eed2f5ebf0034eb",
      "discovered": "2026-04-21T00:00:00Z"
    },
    {
      "version": "v1.1.6",
      "commit": "c07363700f8f942c9cb556006ca9ce5ef1fe9f1f",
      "discovered": "2026-04-21T00:00:00Z"
    },
    {
      "version": "v1.1.5",
      "commit": "c86571de852cb2d8463f5784c7c663a0abf1e437",
      "discovered": "2026-04-21T00:00:00Z"
    },
    {
      "version": "v1.1.4",
      "commit": "5e4990f474391580dec42618896f615925ea724a",
      "discovered": "2026-04-21T00:00:00Z"
    },
    {
      "version": "v1.1.3",
      "commit": "654c7d83389b5e03060f8195fe5b9e105150ce5b",
      "discovered": "2026-04-21T00:00:00Z"
    },
    {
      "version": "v1.1.2",
      "commit": "654c7d83389b5e03060f8195fe5b9e105150ce5b",
      "discovered": "2026-04-21T00:00:00Z"
    },
    {
      "version": "v1.1.1",
      "commit": "d990762f60d3e58279648c09e2b114cab62c8880",
      "discovered": "2026-04-21T00:00:00Z"
    },
    {
      "version": "v1.1.0",
      "commit": "ac04d87cb3fc99d1dc9b7941ab6b4357de23c966",
      "discovered": "2026-04-21T00:00:00Z"
    },
    {
      "version": "v0.1.1",
      "commit": "74e10f5b04f8389c656f0953c8ed08aebf68405c",
      "discovered": "2026-04-21T00:00:00Z"
    },
    {
      "version": "v0.1.0",
      "commit": "bc9a72845879bf0bda2c4c540cfd79f2e033ad0b",
      "discovered": "2026-04-21T00:00:00Z"
    }
  ]
}