{
  "versions": [
    {
      "version": "v0.7.0",
      "commit": "ade9ec1fe6a9ac659fd79b13c591ddd00d379d5e",
      "discovered": "2026-04-21T00:00:00Z"
    },
    {
      "version": "v0.6.3",
      "commit": "2f58f27316a4d783c7910809fdc068c69670941e",
      "discovered": "2026-04-21T00:00:00Z"
    },
    {
      "version": "v0.6.2",
      "commit": "611294e3ba0a3946ca4291503efb0c0b30d62004",
      "discovered": "2026-04-21T00:00:00Z"
    },
    {
      "version": "v0.6.1",
      "commit": "c3e2bb80b492680f4341e56c6297652a6c1e4f00",
      "discovered": "2026-04-21T00:00:00Z"
    },
    {
      "version": "v0.6.0",
      "commit": "930fd792fe857ab5359e43fdff3fe9eb335fb8b2",
      "discovered": "2026-04-21T00:00:00Z"
    }
  ]
}