{
  "versions": [
    {
      "version": "0.6.0",
      "commit": "664234f211c5db5be70e9706053b0ab6095f75fe",
      "discovered": "2026-04-21T00:00:00Z"
    },
    {
      "version": "0.5.0",
      "commit": "553f6f423713fa7d4c4a1d85e9ccc5874b726a31",
      "discovered": "2026-04-21T00:00:00Z"
    },
    {
      "version": "0.4.0",
      "commit": "5ef622c84b1378cc2cc59685a697664b17dd4310",
      "discovered": "2026-04-21T00:00:00Z"
    },
    {
      "version": "0.3.0",
      "commit": "1d07ac72c1f64fc86eea1a46d2b65a057c232966",
      "discovered": "2026-04-21T00:00:00Z"
    },
    {
      "version": "0.2.0",
      "commit": "618bdf678af64a6e69b10e53b404f659dc1838e1",
      "discovered": "2026-04-21T00:00:00Z"
    },
    {
      "version": "0.1.0",
      "commit": "bf46ceecd0323b933728a66ea6b39c5ff7d29b30",
      "discovered": "2026-04-21T00:00:00Z"
    }
  ]
}