{
  "versions": [
    {
      "version": "0.4.0",
      "commit": "518a22b05785e49a9e36c64657eeae801974266a",
      "discovered": "2026-04-21T00:00:00Z"
    },
    {
      "version": "0.3.1",
      "commit": "b30f7b4a66c7873ec4ad1fbaa3d7c5f7fe6380ea",
      "discovered": "2026-04-21T00:00:00Z"
    },
    {
      "version": "0.3.0",
      "commit": "225c2ce39cfb3e03c0787faa5d7fcccf50e6afbe",
      "discovered": "2026-04-21T00:00:00Z"
    },
    {
      "version": "0.2.0",
      "commit": "0f58d8c95ee27fd748ad63c6a71cec498a010bf9",
      "discovered": "2026-04-21T00:00:00Z"
    },
    {
      "version": "0.1.1",
      "commit": "408f59a83de7b1d7d5f8fef4b26b220c7f89b017",
      "discovered": "2026-04-21T00:00:00Z"
    },
    {
      "version": "0.1.0",
      "commit": "f6e3e19e886792eeea0306ec1b4c8b7f3e548844",
      "discovered": "2026-04-21T00:00:00Z"
    }
  ]
}