{
  "versions": [
    {
      "version": "v1.0.4",
      "commit": "656715079bb6ed13aca2a66b97b2f08cb4f87687",
      "discovered": "2026-04-21T00:00:00Z"
    },
    {
      "version": "v1.0.3",
      "commit": "8f065165443a8c613b4a3690e728a00e65db6ab0",
      "discovered": "2026-04-21T00:00:00Z"
    },
    {
      "version": "v1.0.2",
      "commit": "4347d4a516e17f8cbe7d9d8f1d866be69e45fc43",
      "discovered": "2026-04-21T00:00:00Z"
    },
    {
      "version": "v1.0.1",
      "commit": "edc3dbdee91f6dde221586cc48037d114e307a04",
      "discovered": "2026-04-21T00:00:00Z"
    },
    {
      "version": "v1.0.0",
      "commit": "228beb26ff10a836a62c031655213c5aef1356e4",
      "discovered": "2026-04-21T00:00:00Z"
    },
    {
      "version": "v0.1",
      "commit": "a6350b24ff705c468e1a9cb85dc0e295a0a58f4d",
      "discovered": "2026-04-21T00:00:00Z"
    },
    {
      "version": "v0.0",
      "commit": "eba15ec3a1f457c158ebeb23a61a7f43c55b15da",
      "discovered": "2026-04-21T00:00:00Z"
    }
  ]
}