{
  "versions": [
    {
      "version": "v0.3.2",
      "commit": "31b55a27dbafac6152dac07dc4197b8553c3eb5d",
      "discovered": "2026-04-21T00:00:00Z"
    },
    {
      "version": "v0.3.0",
      "commit": "341fc3d72fc810fbcbca33cbf1ecfe7ef58d13b5",
      "discovered": "2026-04-21T00:00:00Z"
    },
    {
      "version": "v0.2.0",
      "commit": "6df90bb28b8b8e26ec547c8e834eed93c5b5199f",
      "discovered": "2026-04-21T00:00:00Z"
    },
    {
      "version": "v0.1.8",
      "commit": "406e17178ae55ae61ae7a70772c5a2e864c75c14",
      "discovered": "2026-04-21T00:00:00Z"
    },
    {
      "version": "v0.1.7",
      "commit": "dd9288532a2edd627b74a8130b43548d14f82bc0",
      "discovered": "2026-04-21T00:00:00Z"
    },
    {
      "version": "v0.1.6",
      "commit": "8c2df0cab5c4bcbc5f98135a787da4eedf8fd491",
      "discovered": "2026-04-21T00:00:00Z"
    },
    {
      "version": "v0.1.5",
      "commit": "685ffb60c56a4a0a3526b3d8ac14fa2c995b3191",
      "discovered": "2026-04-21T00:00:00Z"
    },
    {
      "version": "v0.1.4",
      "commit": "c7271e6558bb25f48f6f11825157d4ddca5cd1ab",
      "discovered": "2026-04-21T00:00:00Z"
    },
    {
      "version": "0.1.2",
      "commit": "a63af862e2adb4eba8bce1a7ee51268692cc09f6",
      "discovered": "2026-04-21T00:00:00Z"
    },
    {
      "version": "0.1.1",
      "commit": "713afa8607af99af806d008ed9fefc9e72363534",
      "discovered": "2026-04-21T00:00:00Z"
    },
    {
      "version": "0.1.0",
      "commit": "b78ca8447f2abde29e559ed7881ac7600d211b74",
      "discovered": "2026-04-21T00:00:00Z"
    }
  ]
}