{
  "versions": [
    {
      "version": "v3.0.6",
      "commit": "3de458b4133c60ca6b3b780aca2ff6999e9cf216",
      "discovered": "2026-04-21T00:00:00Z"
    },
    {
      "version": "v3.0.5",
      "commit": "0a167a2c89ab3615dd0234dd200c3f4e4844b158",
      "discovered": "2026-04-21T00:00:00Z"
    },
    {
      "version": "v3.0.4",
      "commit": "cae598cde94ff19402db5674ff845e8f79ae401e",
      "discovered": "2026-04-21T00:00:00Z"
    },
    {
      "version": "v3.0.3",
      "commit": "49a88a0d05415580ed03f98f712d0da005ea21f8",
      "discovered": "2026-04-21T00:00:00Z"
    },
    {
      "version": "v3.0.2",
      "commit": "891fb9aecb4384f809bbd7528d43c9212d48bcd0",
      "discovered": "2026-04-21T00:00:00Z"
    },
    {
      "version": "v3.0.1",
      "commit": "741a83beb6247a7d0dcec5e928457594c7b15342",
      "discovered": "2026-04-21T00:00:00Z"
    },
    {
      "version": "v3.0.0",
      "commit": "e6332cdd7daf1b7fa004e248b58b07c7727660f7",
      "discovered": "2026-04-21T00:00:00Z"
    },
    {
      "version": "v2.3.2",
      "commit": "50cf3ab16d9dc11e6e1d4abd6d971152971cde9f",
      "discovered": "2026-04-21T00:00:00Z"
    },
    {
      "version": "v2.3.1",
      "commit": "df6830573f2832e9a50e419c8284c133fda19463",
      "discovered": "2026-04-21T00:00:00Z"
    },
    {
      "version": "v2.3.0",
      "commit": "de560dd92c8c9ec4d32b7a7d1991d8117a008d62",
      "discovered": "2026-04-21T00:00:00Z"
    },
    {
      "version": "v2.2.4",
      "commit": "1ea939e6f212642c7fcb81b1f3f251a25e82a105",
      "discovered": "2026-04-21T00:00:00Z"
    },
    {
      "version": "v2.2.3",
      "commit": "1200098071b2a19129febda403f1bc9397202c43",
      "discovered": "2026-04-21T00:00:00Z"
    },
    {
      "version": "v2.2.2",
      "commit": "d2708d5f90b5104ecc97a017af72afba708b99e1",
      "discovered": "2026-04-21T00:00:00Z"
    },
    {
      "version": "v2.2.1",
      "commit": "07e96bfe139562b6c06b14dd6cb8f679dde0ec1a",
      "discovered": "2026-04-21T00:00:00Z"
    },
    {
      "version": "v2.2.0",
      "commit": "2d5f206f046194094dd58672d81d54cfe96dfb88",
      "discovered": "2026-04-21T00:00:00Z"
    },
    {
      "version": "v2.1.0",
      "commit": "d6a9ce2debbb26faac59bcdf9937cff60064070a",
      "discovered": "2026-04-21T00:00:00Z"
    },
    {
      "version": "v2.0.1",
      "commit": "2405734b958d75d4fbe0b61fb5219fc8ca643806",
      "discovered": "2026-04-21T00:00:00Z"
    },
    {
      "version": "v2.0.0",
      "commit": "ddfdfda635f33dc978b05bbfc2ddcc54ae6159b8",
      "discovered": "2026-04-21T00:00:00Z"
    },
    {
      "version": "v1.2.1",
      "commit": "6f36e26023605fafb2659e46eb54740624553b40",
      "discovered": "2026-04-21T00:00:00Z"
    },
    {
      "version": "v1.2.0",
      "commit": "058c1c2045a7627994c9c6714e2147a2d0325530",
      "discovered": "2026-04-21T00:00:00Z"
    },
    {
      "version": "v1.1.3",
      "commit": "95a867f6fead9863333024ae53dd60ad80ab0c60",
      "discovered": "2026-04-21T00:00:00Z"
    },
    {
      "version": "v1.1.2",
      "commit": "c1acebeb3b47e02d9f6918a332cfb7c7111e4d97",
      "discovered": "2026-04-21T00:00:00Z"
    },
    {
      "version": "v1.1.1",
      "commit": "8116799c66e26d833255ae3d62ab63b8a19f3b1c",
      "discovered": "2026-04-21T00:00:00Z"
    },
    {
      "version": "1.1.0",
      "commit": "240b2b24e80f79a030912a77168516a97864903d",
      "discovered": "2026-04-21T00:00:00Z"
    },
    {
      "version": "1.0.5",
      "commit": "f0361e96e10cb2c411c0814d9c3c20e6f2bf337e",
      "discovered": "2026-04-21T00:00:00Z"
    },
    {
      "version": "v1.0.4",
      "commit": "e73ca7d9fdebf1d87c31100dd73184208df4b555",
      "discovered": "2026-04-21T00:00:00Z"
    },
    {
      "version": "v1.0.3",
      "commit": "b923ef083462eb24b60d0163f7266c0d8bf93d76",
      "discovered": "2026-04-21T00:00:00Z"
    },
    {
      "version": "v1.0.2",
      "commit": "a2f183fdd6a645592a4dfabd80acf65e9937032b",
      "discovered": "2026-04-21T00:00:00Z"
    },
    {
      "version": "v1.0.1",
      "commit": "d1072a2c698c2a6e253355aad360ecf31b916815",
      "discovered": "2026-04-21T00:00:00Z"
    }
  ]
}