{
  "versions": [
    {
      "version": "v0.3.0",
      "commit": "f0ce5990c238a1872664af7c65a138efc436f4e0",
      "discovered": "2026-04-21T00:00:00Z"
    },
    {
      "version": "v0.2.1",
      "commit": "916765af218a5e9a864ebc81635a71a32d2e2f4b",
      "discovered": "2026-04-21T00:00:00Z"
    },
    {
      "version": "v0.2.0",
      "commit": "6e554cbeee5afbf5676c5cfbea5831e88c99d647",
      "discovered": "2026-04-21T00:00:00Z"
    },
    {
      "version": "v0.1.3",
      "commit": "0a15c7e934418cba812865a99315aba86e8fc4fa",
      "discovered": "2026-04-21T00:00:00Z"
    },
    {
      "version": "v0.1.2",
      "commit": "741f4a36408038157c698c95f85f0b8cf18eb3c5",
      "discovered": "2026-04-21T00:00:00Z"
    },
    {
      "version": "v0.1.1",
      "commit": "0dea9925a45bfe54c169e989762e8a038600c524",
      "discovered": "2026-04-21T00:00:00Z"
    },
    {
      "version": "v0.1.0",
      "commit": "201f1edd1b0e4717df1290135d992725464e6be0",
      "discovered": "2026-04-21T00:00:00Z"
    }
  ]
}