{
  "versions": [
    {
      "version": "v1.0.6",
      "commit": "1ff740bf3c06cd25059562f4a11d88f12ebbc5ee",
      "discovered": "2026-04-21T00:00:00Z"
    },
    {
      "version": "v1.0.5",
      "commit": "03a247ce0d40df6035d894ff04c0ee04c7869366",
      "discovered": "2026-04-21T00:00:00Z"
    },
    {
      "version": "v1.0.4",
      "commit": "8b3f544aa26ac305869a9d57ed2d1456271637f8",
      "discovered": "2026-04-21T00:00:00Z"
    },
    {
      "version": "v1.0.3",
      "commit": "a0f7fd2f86d0ff793eb413f1c9fd573fedb987e8",
      "discovered": "2026-04-21T00:00:00Z"
    },
    {
      "version": "v1.0.2",
      "commit": "b4c235390c191445f9e32d82863bcdb64633bba3",
      "discovered": "2026-04-21T00:00:00Z"
    },
    {
      "version": "1.0.1",
      "commit": "79b3181966909302eaf9dcd159b597448c60ee2f",
      "discovered": "2026-04-21T00:00:00Z"
    },
    {
      "version": "1.0.0",
      "commit": "343520944c30e5431d542be3b699776d5ae34a32",
      "discovered": "2026-04-21T00:00:00Z"
    }
  ]
}