{
  "versions": [
    {
      "version": "v0.1.3",
      "commit": "ad736d6508efb0002cc4c520e97ecc475bb03a09",
      "discovered": "2026-04-21T00:00:00Z"
    },
    {
      "version": "v0.1.2",
      "commit": "1e1089f912028bef0e301719b38ef5d4e2fcd439",
      "discovered": "2026-04-21T00:00:00Z"
    },
    {
      "version": "v0.1.1",
      "commit": "e6011b5a2374c3190d9f30bef0489c284bbe82a4",
      "discovered": "2026-04-21T00:00:00Z"
    },
    {
      "version": "v0.1.0",
      "commit": "b0fb59aa28ccbbc5c759d4d42f29139a15f927a5",
      "discovered": "2026-04-21T00:00:00Z"
    }
  ]
}