{
  "versions": [
    {
      "version": "v1.1",
      "commit": "e8419bd2f3c4c733c4ae688d8339e039cdd05cf3",
      "discovered": "2026-04-21T00:00:00Z"
    },
    {
      "version": "v1.0.2",
      "commit": "02ba0b0a0933ebc23669bff0d37b4d43dc4cf33b",
      "discovered": "2026-04-21T00:00:00Z"
    },
    {
      "version": "v1.0.1",
      "commit": "c20ba306f7750961fac207dfb5df397aac238458",
      "discovered": "2026-04-21T00:00:00Z"
    },
    {
      "version": "v1.0",
      "commit": "a83be56450306d8fabbf6722c919ac3c84e3b673",
      "discovered": "2026-04-21T00:00:00Z"
    }
  ]
}