{
  "versions": [
    {
      "version": "v0.2.5",
      "commit": "4cee783571d13dd476064aaf2d8db421feadf788",
      "discovered": "2026-04-21T00:00:00Z"
    },
    {
      "version": "v0.2.3",
      "commit": "828f8d231c3423affb9783f9789bc41a70b39061",
      "discovered": "2026-04-21T00:00:00Z"
    },
    {
      "version": "v0.2.2",
      "commit": "28e3cf23103917f17ec2613b4def1c64af18c3ea",
      "discovered": "2026-04-21T00:00:00Z"
    },
    {
      "version": "v0.2.1",
      "commit": "6bbdf0e43d9ce1013ae3095a7e678d0ddbcc7bc4",
      "discovered": "2026-04-21T00:00:00Z"
    },
    {
      "version": "v0.2.0",
      "commit": "48d937d36b5dc488af0dba70e8ea12b8b5d2e20b",
      "discovered": "2026-04-21T00:00:00Z"
    },
    {
      "version": "v0.1.0",
      "commit": "3d790b9517ad84617e1c9346853580f388714bac",
      "discovered": "2026-04-21T00:00:00Z"
    }
  ]
}