{
  "versions": [
    {
      "version": "v0.3.0",
      "commit": "a2ade5c204c22fe8295c6e2b3f8163fb1f24fa02",
      "discovered": "2026-04-21T00:00:00Z"
    },
    {
      "version": "v0.2.5",
      "commit": "85ed12e390307ad975e630a7225ed4b8bab4c165",
      "discovered": "2026-04-21T00:00:00Z"
    },
    {
      "version": "v0.2.4",
      "commit": "07d8846ecb64fe2a935aadaf36120be8f40fca82",
      "discovered": "2026-04-21T00:00:00Z"
    },
    {
      "version": "v0.2.3",
      "commit": "e809c82e057b80c0a3f2bd81a93f90ff0aff94aa",
      "discovered": "2026-04-21T00:00:00Z"
    },
    {
      "version": "v0.2.2",
      "commit": "e809c82e057b80c0a3f2bd81a93f90ff0aff94aa",
      "discovered": "2026-04-21T00:00:00Z"
    },
    {
      "version": "v0.2.1",
      "commit": "df6d53a5d47f7f62f62136046de9ade57364d174",
      "discovered": "2026-04-21T00:00:00Z"
    },
    {
      "version": "v0.2.0",
      "commit": "0944ce692d70cb2b746469b7b00e4066b2b66bb2",
      "discovered": "2026-04-21T00:00:00Z"
    },
    {
      "version": "v0.1.5",
      "commit": "d827c3dad6d9bb9bfe76cd86241771ab45a24867",
      "discovered": "2026-04-21T00:00:00Z"
    },
    {
      "version": "v0.1.4",
      "commit": "6c24c3e24e1e615313ac635ccd190ae671a095d1",
      "discovered": "2026-04-21T00:00:00Z"
    },
    {
      "version": "v0.1.3",
      "commit": "717fe00990ef721dfca84532ce2ad601d82a4cb9",
      "discovered": "2026-04-21T00:00:00Z"
    },
    {
      "version": "v0.1.2",
      "commit": "acfefc7e986bf47bf3d6c3ab2a175f9b8e1bc7f3",
      "discovered": "2026-04-21T00:00:00Z"
    },
    {
      "version": "v0.1.1",
      "commit": "a154a78e07da9b2d8310729eef8ca1483568a08e",
      "discovered": "2026-04-21T00:00:00Z"
    },
    {
      "version": "v0.1.0",
      "commit": "1c8c1028fdbc44db7effd0e0356d99f14ec0aa69",
      "discovered": "2026-04-21T00:00:00Z"
    }
  ]
}